iostuff/__init__.py
iostuff/common.py
iostuff/readers.py
iostuff/writers.py
iostuff-0.4.0.dist-info/METADATA
iostuff-0.4.0.dist-info/WHEEL
iostuff-0.4.0.dist-info/RECORD
