Metadata-Version: 2.1
Name: iostuff
Version: 0.4.0
Summary: 
Author: bqio
Author-email: dmitry.mikhaltsov98@gmail.com
Requires-Python: >=3.12,<4.0
Classifier: Programming Language :: Python :: 3
Requires-Dist: jsonpickle (>=3.0.2,<4.0.0)
